src/control.v
`timescale 1ns/ 1ps

module control (
    input wire [6:0] opcode,
    input wire [2:0] funct3,
    input wire funct7_b5, //distinguishes action
    output reg reg_write,
    output reg alu_src, //0=rs2, 1=imm
    output reg branch,
    output reg [3:0 ] alu_ctrl
);

    localparam OP_R_TYPE = 7'b0110011; // add, sub, and, or, xor, sll, srl, sra, slt, sltu
    localparam OP_I_TYPE = 7'b0010011; // addi, and
    localparam OP_B_TYPE = 7'b1100011; // beq, bne, blt, bge, bltu, bgeu

    localparam ALU_ADD  = 4'b0000;
    localparam ALU_SUB  = 4'b0001;
    localparam ALU_AND  = 4'b0010;
    localparam ALU_OR   = 4'b0011;
    localparam ALU_XOR  = 4'b0100;
    localparam ALU_SLL  = 4'b0101;
    localparam ALU_SRL  = 4'b0110;
    localparam ALU_SRA  = 4'b0111;
    localparam ALU_SLT  = 4'b1000;
    localparam ALU_SLTU = 4'b1001;

    always @(*) begin
        reg_write = 1'b0;
        alu_src = 1'b0;
        branch = 1'b0;
        alu_ctrl = ALU_ADD;

        case (opcode)
            OP_R_TYPE: begin
                reg_write = 1'b1;
                alu_src = 1'b0; //rs2
                branch = 1'b0;
                case (funct3)
                    3'b000: alu_ctrl = funct7_b5 ? ALU_SUB : ALU_ADD; //add/sub
                    3'b111: alu_ctrl = ALU_AND;
                    3'b110: alu_ctrl = ALU_OR;
                    3'b100: alu_ctrl = ALU_XOR;
                    3'b001: alu_ctrl = ALU_SLL;
                    3'b101: alu_ctrl = funct7_b5 ? ALU_SRA : ALU_SRL; //srl/sra
                    3'b010: alu_ctrl = ALU_SLT;
                    3'b011: alu_ctrl = ALU_SLTU;
                    default: alu_ctrl = ALU_ADD; //default to add
                endcase
            end

            OP_I_TYPE: begin
                reg_write = 1'b1;
                alu_src = 1'b1; //imm
                branch = 1'b0;
                case (funct3)
                    3'b000: alu_ctrl = ALU_ADD; //addi
                    3'b111: alu_ctrl = ALU_AND; //andi
                    3'b110: alu_ctrl = ALU_OR;  //ori
                    3'b100: alu_ctrl = ALU_XOR; //xori
                    3'b001: alu_ctrl = ALU_SLL; //slli
                    3'b101: alu_ctrl = funct7_b5 ? ALU_SRA : ALU_SRL; //srli/srai
                    3'b010: alu_ctrl = ALU_SLT; //slti
                    3'b011: alu_ctrl = ALU_SLTU; //sltiu
                    default: alu_ctrl = ALU_ADD; //default to addi
                endcase
            end

            OP_B_TYPE: begin
                reg_write = 1'b0;
                alu_src = 1'b0; //rs2
                branch = 1'b1;
                alu_ctrl = ALU_SUB; //for branch comparison
            end

            default: begin
                reg_write = 1'b0;
                alu_src = 1'b0;
                branch = 1'b0;
                alu_ctrl = ALU_ADD; //default to add
            end
        endcase
    end
endmodule

tests/control_tb.v
`timescale 1ns / 1ps

module control_tb;

    reg  [6:0] opcode;
    reg  [2:0] funct3;
    reg        funct7_b5;
    wire       reg_write;
    wire       alu_src;
    wire       branch;
    wire [3:0] alu_ctrl;
 
    integer    errors = 0;
    integer    checks = 0;
 
    localparam ALU_ADD  = 4'b0000;
    localparam ALU_SUB  = 4'b0001;
    localparam ALU_AND  = 4'b0010;
    localparam ALU_OR   = 4'b0011;
    localparam ALU_XOR  = 4'b0100;
    localparam ALU_SLT  = 4'b1000;
    localparam ALU_SLTU = 4'b1001;
 
    control dut (
        .opcode    (opcode),
        .funct3    (funct3),
        .funct7_b5 (funct7_b5),
        .reg_write (reg_write),
        .alu_src   (alu_src),
        .branch    (branch),
        .alu_ctrl  (alu_ctrl)
    );
 
    task check(input rw_exp, input src_exp, input br_exp, input [3:0] alu_exp, input string label);
        begin
            #1;
            checks = checks + 1;
            if (reg_write !== rw_exp || alu_src !== src_exp || branch !== br_exp || alu_ctrl !== alu_exp) begin
                errors = errors + 1;
                $display("[FAIL] %0s: expected rw=%0b src=%0b br=%0b alu=%0b, got rw=%0b src=%0b br=%0b alu=%0b",
                          label, rw_exp, src_exp, br_exp, alu_exp, reg_write, alu_src, branch, alu_ctrl);
            end else begin
                $display("[PASS] %0s: rw=%0b src=%0b br=%0b alu=%0b", label, reg_write, alu_src, branch, alu_ctrl);
            end
        end
    endtask
 
    initial begin
        $dumpfile("control_tb.vcd");
        $dumpvars(0, control_tb);
 
        // R-type: add (funct3=000, funct7[5]=0)
        opcode = 7'b0110011; funct3 = 3'b000; funct7_b5 = 1'b0;
        check(1, 0, 0, ALU_ADD, "R-type add");
 
        // R-type: sub (same funct3, funct7[5]=1 -- the classic add/sub disambiguation)
        opcode = 7'b0110011; funct3 = 3'b000; funct7_b5 = 1'b1;
        check(1, 0, 0, ALU_SUB, "R-type sub");
 
        // R-type: and, or, xor, slt, sltu
        opcode = 7'b0110011; funct3 = 3'b111; funct7_b5 = 1'b0;
        check(1, 0, 0, ALU_AND, "R-type and");
 
        opcode = 7'b0110011; funct3 = 3'b110; funct7_b5 = 1'b0;
        check(1, 0, 0, ALU_OR, "R-type or");
 
        opcode = 7'b0110011; funct3 = 3'b100; funct7_b5 = 1'b0;
        check(1, 0, 0, ALU_XOR, "R-type xor");
 
        opcode = 7'b0110011; funct3 = 3'b010; funct7_b5 = 1'b0;
        check(1, 0, 0, ALU_SLT, "R-type slt");
 
        opcode = 7'b0110011; funct3 = 3'b011; funct7_b5 = 1'b0;
        check(1, 0, 0, ALU_SLTU, "R-type sltu");
 
        // I-type: addi -- note funct7_b5 is irrelevant here since it's part
        // of the immediate field for I-type, not a real funct7 bit
        opcode = 7'b0010011; funct3 = 3'b000; funct7_b5 = 1'b0;
        check(1, 1, 0, ALU_ADD, "I-type addi");
 
        // I-type: andi
        opcode = 7'b0010011; funct3 = 3'b111; funct7_b5 = 1'b0;
        check(1, 1, 0, ALU_AND, "I-type andi");
 
        // B-type: beq/bne share the same control signals (SUB + branch=1);
        // the equal-vs-not-equal distinction happens outside this module
        opcode = 7'b1100011; funct3 = 3'b000; funct7_b5 = 1'b0;
        check(0, 0, 1, ALU_SUB, "B-type beq");
 
        opcode = 7'b1100011; funct3 = 3'b001; funct7_b5 = 1'b0;
        check(0, 0, 1, ALU_SUB, "B-type bne");
 
        // Unknown/unsupported opcode: should default safely (no writes, no branch)
        opcode = 7'b1111111; funct3 = 3'b000; funct7_b5 = 1'b0;
        check(0, 0, 0, ALU_ADD, "Unknown opcode defaults safely");
 
        $display("--------------------------------------------------");
        if (errors == 0)
            $display("ALL %0d CHECKS PASSED", checks);
        else
            $display("%0d OF %0d CHECKS FAILED", errors, checks);
        $display("--------------------------------------------------");
 
        $finish;
    end
 
endmodule

control_tb.vcd
$version Generated by VerilatedVcd $end
$timescale 1ps $end
 $scope module $rootio $end
 $upscope $end
 $scope module control_tb $end
  $var wire 7 # opcode [6:0] $end
  $var wire 3 $ funct3 [2:0] $end
  $var wire 1 % funct7_b5 $end
  $var wire 1 ( reg_write $end
  $var wire 1 ) alu_src $end
  $var wire 1 * branch $end
  $var wire 4 + alu_ctrl [3:0] $end
  $var wire 32 & errors [31:0] $end
  $var wire 32 ' checks [31:0] $end
  $var wire 4 , ALU_ADD [3:0] $end
  $var wire 4 - ALU_SUB [3:0] $end
  $var wire 4 . ALU_AND [3:0] $end
  $var wire 4 / ALU_OR [3:0] $end
  $var wire 4 0 ALU_XOR [3:0] $end
  $var wire 4 1 ALU_SLT [3:0] $end
  $var wire 4 2 ALU_SLTU [3:0] $end
  $scope module dut $end
   $var wire 7 # opcode [6:0] $end
   $var wire 3 $ funct3 [2:0] $end
   $var wire 1 % funct7_b5 $end
   $var wire 1 ( reg_write $end
   $var wire 1 ) alu_src $end
   $var wire 1 * branch $end
   $var wire 4 + alu_ctrl [3:0] $end
   $var wire 7 3 OP_R_TYPE [6:0] $end
   $var wire 7 4 OP_I_TYPE [6:0] $end
   $var wire 7 5 OP_B_TYPE [6:0] $end
   $var wire 4 , ALU_ADD [3:0] $end
   $var wire 4 - ALU_SUB [3:0] $end
   $var wire 4 . ALU_AND [3:0] $end
   $var wire 4 / ALU_OR [3:0] $end
   $var wire 4 0 ALU_XOR [3:0] $end
   $var wire 4 6 ALU_SLL [3:0] $end
   $var wire 4 7 ALU_SRL [3:0] $end
   $var wire 4 8 ALU_SRA [3:0] $end
   $var wire 4 1 ALU_SLT [3:0] $end
   $var wire 4 2 ALU_SLTU [3:0] $end
  $upscope $end
 $upscope $end
$enddefinitions $end


#0
b0110011 #
b000 $
0%
b00000000000000000000000000000000 &
b00000000000000000000000000000000 '
1(
0)
0*
b0000 +
b0000 ,
b0001 -
b0010 .
b0011 /
b0100 0
b1000 1
b1001 2
b0110011 3
b0010011 4
b1100011 5
b0101 6
b0110 7
b0111 8
#1000
1%
b00000000000000000000000000000001 '
b0001 +
#2000
b111 $
0%
b00000000000000000000000000000010 '
b0010 +
#3000
b110 $
b00000000000000000000000000000011 '
b0011 +
#4000
b100 $
b00000000000000000000000000000100 '
b0100 +
#5000
b010 $
b00000000000000000000000000000101 '
b1000 +
#6000
b011 $
b00000000000000000000000000000110 '
b1001 +
#7000
b0010011 #
b000 $
b00000000000000000000000000000111 '
1)
b0000 +
#8000
b111 $
b00000000000000000000000000001000 '
b0010 +
#9000
b1100011 #
b000 $
b00000000000000000000000000001001 '
0(
0)
1*
b0001 +
#10000
b001 $
b00000000000000000000000000001010 '
#11000
b1111111 #
b000 $
b00000000000000000000000000001011 '
0*
b0000 +
#12000
b00000000000000000000000000001100 '
