src/alu.v
`timescale 1ns / 1ps

module alu (
    input wire [31:0] a,
    input wire [31:0] b,
    input wire [3:0]  alu_ctrl,
    output reg [31:0] result,
    output wire zero
    );

    localparam ALU_ADD  = 4'b0000;
    localparam ALU_SUB  = 4'b0001;
    localparam ALU_AND  = 4'b0010;
    localparam ALU_OR   = 4'b0011;
    localparam ALU_XOR  = 4'b0100;
    localparam ALU_SLL  = 4'b0101;
    localparam ALU_SRL  = 4'b0110;
    localparam ALU_SRA  = 4'b0111;
    localparam ALU_SLT  = 4'b1000;
    localparam ALU_SLTU = 4'b1001;

    always @(*)
    begin
        case (alu_ctrl)
            ALU_ADD:  result = a + b;
            ALU_SUB:  result = a - b;
            ALU_AND:  result = a & b;
            ALU_OR:   result = a | b;
            ALU_XOR:  result = a ^ b;
            ALU_SLL:  result = a << b[4:0]; //shift bottom 5 bits
            ALU_SRL:  result = a >> b[4:0];
            ALU_SRA:  result = $signed(a) >>> b[4:0]; //arithmetic preserves sign bit
            ALU_SLT:  result = ($signed(a) < $signed(b)) ? 32'b1 : 32'b0; //compare signed values
            ALU_SLTU: result = (a < b) ? 32'b1 : 32'b0; //compare unsigned values
            default:  result = 32'b0; // Default case to avoid latches
        endcase
    end

    assign zero = (result == 32'b0); // used by control unit fr branches

endmodule

src/control.v
`timescale 1ns/ 1ps

module control (
    input wire [6:0] opcode,
    input wire [2:0] funct3,
    input wire funct7_b5, //distinguishes action
    output reg reg_write,
    output reg alu_src, //0=rs2, 1=imm
    output reg branch,
    output reg [3:0 ] alu_ctrl
);

    localparam OP_R_TYPE = 7'b0110011; // add, sub, and, or, xor, sll, srl, sra, slt, sltu
    localparam OP_I_TYPE = 7'b0010011; // addi, and
    localparam OP_B_TYPE = 7'b1100011; // beq, bne, blt, bge, bltu, bgeu

    localparam ALU_ADD  = 4'b0000;
    localparam ALU_SUB  = 4'b0001;
    localparam ALU_AND  = 4'b0010;
    localparam ALU_OR   = 4'b0011;
    localparam ALU_XOR  = 4'b0100;
    localparam ALU_SLL  = 4'b0101;
    localparam ALU_SRL  = 4'b0110;
    localparam ALU_SRA  = 4'b0111;
    localparam ALU_SLT  = 4'b1000;
    localparam ALU_SLTU = 4'b1001;

    always @(*) begin
        reg_write = 1'b0;
        alu_src = 1'b0;
        branch = 1'b0;
        alu_ctrl = ALU_ADD;

        case (opcode)
            OP_R_TYPE: begin
                reg_write = 1'b1;
                alu_src = 1'b0; //rs2
                branch = 1'b0;
                case (funct3)
                    3'b000: alu_ctrl = funct7_b5 ? ALU_SUB : ALU_ADD; //add/sub
                    3'b111: alu_ctrl = ALU_AND;
                    3'b110: alu_ctrl = ALU_OR;
                    3'b100: alu_ctrl = ALU_XOR;
                    3'b001: alu_ctrl = ALU_SLL;
                    3'b101: alu_ctrl = funct7_b5 ? ALU_SRA : ALU_SRL; //srl/sra
                    3'b010: alu_ctrl = ALU_SLT;
                    3'b011: alu_ctrl = ALU_SLTU;
                    default: alu_ctrl = ALU_ADD; //default to add
                endcase
            end

            OP_I_TYPE: begin
                reg_write = 1'b1;
                alu_src = 1'b1; //imm
                branch = 1'b0;
                case (funct3)
                    3'b000: alu_ctrl = ALU_ADD; //addi
                    3'b111: alu_ctrl = ALU_AND; //andi
                    3'b110: alu_ctrl = ALU_OR;  //ori
                    3'b100: alu_ctrl = ALU_XOR; //xori
                    3'b001: alu_ctrl = ALU_SLL; //slli
                    3'b101: alu_ctrl = funct7_b5 ? ALU_SRA : ALU_SRL; //srli/srai
                    3'b010: alu_ctrl = ALU_SLT; //slti
                    3'b011: alu_ctrl = ALU_SLTU; //sltiu
                    default: alu_ctrl = ALU_ADD; //default to addi
                endcase
            end

            OP_B_TYPE: begin
                reg_write = 1'b0;
                alu_src = 1'b0; //rs2
                branch = 1'b1;
                alu_ctrl = ALU_SUB; //for branch comparison
            end

            default: begin
                reg_write = 1'b0;
                alu_src = 1'b0;
                branch = 1'b0;
                alu_ctrl = ALU_ADD; //default to add
            end
        endcase
    end
endmodule

src/immgen.v
`timescale 1ns / 1ps

module immgen (
    input wire [31:0] instr,
    output reg [31:0] imm
);

    localparam OP_I_TYPE = 7'b0010011; // addi, andi, ori, xori, slli, srli, srai
    localparam OP_B_TYPE = 7'b1100011; // beq, bne, blt, bge, bltu, bgeu

    always @(*) begin
        case (instr[6:0])
            OP_I_TYPE:
                // I-type immediate: bits [31:20]
                imm = {{20{instr[31]}}, instr[31:20]}; // sign-extend
            OP_B_TYPE:
                // B-type immediate: bits [31], [7], [30:25], [11:8]
                imm = {{19{instr[31]}}, instr[31], instr[7], instr[30:25], instr[11:8], 1'b0}; // sign-extend and shift left by 1
            default:
                imm = 32'b0; // Default case to avoid latches
        endcase
    end
endmodule

src/regfile.v
`timescale 1ns / 1ps

module regfile (
    input wire clk,
    input wire rst,
    input wire [4:0] rs1_addr,
    input wire [4:0] rs2_addr,
    input wire [4:0] rd_addr,
    input wire [31:0] rd_data,
    input wire reg_write,
    output reg [31:0] rs1_data,
    output reg [31:0] rs2_data
);

    // Register file: 32 registers of 32 bits each
    reg [31:0] registers [31:0];

    // Initialize registers to zero on reset
    integer i;
    always @(posedge clk or posedge rst) begin
        if (rst) begin
            for (i = 0; i < 32; i = i + 1) begin
                registers[i] <= 32'b0;
            end
        end else if (reg_write && rd_addr != 5'b00000) begin
            // Write to the register file on the rising edge of the clock
            registers[rd_addr] <= rd_data;
        end
    end

    // --- Read logic: combinational, always available ---
    // x0 is hardwired to zero: if either read address is 0, force output
    // to 0 regardless of what's actually stored there (which will also be
    // 0 after reset, but this makes the guarantee explicit and independent
    // of reset having run).
    assign rs1_data = (rs1_addr == 5'b0) ? 32'b0 : registers[rs1_addr];
    assign rs2_data = (rs2_addr == 5'b0) ? 32'b0 : registers[rs2_addr];

endmodule

src/imem.v
`timescale 1ns / 1ps

module imem #(
    parameter MEM_SIZE_WORDS = 256   // number of 32-bit instruction words
) (
    input  wire [31:0] addr,          // byte address, from PC (must be word-aligned)
    output wire [31:0] instr
);

    // Memory modeled as an array of 32-bit words.
    reg [31:0] mem [0:MEM_SIZE_WORDS-1];

    // Zero-initialize for deterministic simulation. On real hardware this
    // would instead be preloaded with your compiled program image (e.g. via
    // $readmemh loading a .hex file generated by the RISC-V toolchain, or
    // synthesized directly into block RAM initial contents on an FPGA).
    integer i;
    initial begin
        for (i = 0; i < MEM_SIZE_WORDS; i = i + 1) begin
            mem[i] = 32'b0;
        end
    end

    // Word-aligned indexing: drop the bottom 2 bits of the byte address.
    // addr[31:2] gives the word index; addr[1:0] would be the byte offset
    // within a word, which we ignore since every valid instruction fetch
    // is word-aligned (addr[1:0] should always be 00 in practice).
    localparam ADDR_WIDTH = $clog2(MEM_SIZE_WORDS);
    assign instr = mem[addr[ADDR_WIDTH+1:2]];

endmodule

src/pc.v
`timescale 1ns / 1ps

module pc (
    input wire clk,
    input wire rst,
    input wire [31:0] pc_next,
    output reg [31:0] pc_out
    );

always @(posedge clk or posedge rst) begin
    if (rst)
        pc_out <= 32'b00; // Reset PC to 0 on reset
    else
        pc_out <= pc_next; // Update PC with the next value
end

endmodule

src/top.v
`timescale 1ns / 1ps

module top (
    input wire clk,
    input wire rst
);

    wire [31:0] pc_out, pc_plus_4, pc_next, branch_target;
    wire [31:0] instr;
    wire [31:0] rs1_data, rs2_data, alu_b, alu_result, imm;
    wire        reg_write, alu_src, branch, zero, branch_taken;
    wire [3:0]  alu_ctrl;
 
    wire [6:0] opcode    = instr[6:0];
    wire [4:0] rd_addr   = instr[11:7];
    wire [2:0] funct3    = instr[14:12];
    wire [4:0] rs1_addr  = instr[19:15];
    wire [4:0] rs2_addr  = instr[24:20];
    wire       funct7_b5 = instr[30];
 
    pc pc_inst (
        .clk     (clk),
        .rst     (rst),
        .pc_next (pc_next),
        .pc_out  (pc_out)
    );
 
    imem imem_inst (
        .addr  (pc_out),
        .instr (instr)
    );
 
    regfile regfile_inst (
        .clk       (clk),
        .rst       (rst),
        .rs1_addr  (rs1_addr),
        .rs1_data  (rs1_data),
        .rs2_addr  (rs2_addr),
        .rs2_data  (rs2_data),
        .reg_write (reg_write),
        .rd_addr   (rd_addr),
        .rd_data   (alu_result)
    );
 
    immgen immgen_inst (
        .instr (instr),
        .imm   (imm)
    );
 
    control control_inst (
        .opcode    (opcode),
        .funct3    (funct3),
        .funct7_b5 (funct7_b5),
        .reg_write (reg_write),
        .alu_src   (alu_src),
        .branch    (branch),
        .alu_ctrl  (alu_ctrl)
    );
 
    assign alu_b = alu_src ? imm : rs2_data;
 
    alu alu_inst (
        .a        (rs1_data),
        .b        (alu_b),
        .alu_ctrl (alu_ctrl),
        .result   (alu_result),
        .zero     (zero)
    );
 
    assign pc_plus_4    = pc_out + 32'd4;
    assign branch_target = pc_out + imm;
    assign branch_taken  = branch & (zero ^ funct3[0]); // beq: funct3[0]=0, bne: funct3[0]=1
    assign pc_next        = branch_taken ? branch_target : pc_plus_4;
 
endmodule

tests/top_tb.v
`timescale 1ns / 1ps

`timescale 1ns / 1ps

module top_tb;

    reg clk;
    reg rst;

    integer errors = 0;
    integer checks = 0;

    top dut (
        .clk (clk),
        .rst (rst)
    );

    initial clk = 0;
    always #5 clk = ~clk;

    task check_reg(input [4:0] reg_num, input [31:0] expected, input string label);
        begin
            checks = checks + 1;
            if (dut.regfile_inst.registers[reg_num] !== expected) begin
                errors = errors + 1;
                $display("[FAIL] %0s: x%0d expected 0x%08h, got 0x%08h",
                          label, reg_num, expected, dut.regfile_inst.registers[reg_num]);
            end else begin
                $display("[PASS] %0s: x%0d = 0x%08h", label, reg_num, dut.regfile_inst.registers[reg_num]);
            end
        end
    endtask

    initial begin
        $dumpfile("top_tb.vcd");
        $dumpvars(0, top_tb);

        rst = 1;

        // Program (7 instructions, one per 4-byte word):
        //   0x00: addi x1, x0, 5          x1 = 5
        //   0x04: addi x2, x0, 10         x2 = 10
        //   0x08: add  x3, x1, x2         x3 = 15
        //   0x0C: sub  x4, x2, x1         x4 = 5
        //   0x10: beq  x1, x4, +8         x1==x4 (5==5) -> branch taken, skip 0x14
        //   0x14: addi x5, x0, 99         SHOULD BE SKIPPED, x5 stays 0
        //   0x18: addi x6, x0, 1          branch target, x6 = 1

        dut.imem_inst.mem[0] = {12'd5,  5'd0, 3'b000, 5'd1, 7'b0010011};
        dut.imem_inst.mem[1] = {12'd10, 5'd0, 3'b000, 5'd2, 7'b0010011};
        dut.imem_inst.mem[2] = {7'b0000000, 5'd2, 5'd1, 3'b000, 5'd3, 7'b0110011};
        dut.imem_inst.mem[3] = {7'b0100000, 5'd1, 5'd2, 3'b000, 5'd4, 7'b0110011};
        dut.imem_inst.mem[4] = {1'b0, 6'b000000, 5'd4, 5'd1, 3'b000, 4'b0100, 1'b0, 7'b1100011};
        dut.imem_inst.mem[5] = {12'd99, 5'd0, 3'b000, 5'd5, 7'b0010011};
        dut.imem_inst.mem[6] = {12'd1,  5'd0, 3'b000, 5'd6, 7'b0010011};

        @(posedge clk);
        #1;
        rst = 0;

        // One instruction retires per clock edge in a single-cycle CPU.
        // Run 7 edges to execute all 7 instructions (branch counts as one).
        repeat (7) @(posedge clk);
        #1;

        check_reg(5'd1, 32'd5,  "x1 = 5 (addi)");
        check_reg(5'd2, 32'd10, "x2 = 10 (addi)");
        check_reg(5'd3, 32'd15, "x3 = 15 (add)");
        check_reg(5'd4, 32'd5,  "x4 = 5 (sub)");
        check_reg(5'd5, 32'd0,  "x5 = 0 (skipped by branch)");
        check_reg(5'd6, 32'd1,  "x6 = 1 (branch target reached)");

        $display("--------------------------------------------------");
        if (errors == 0)
            $display("ALL %0d CHECKS PASSED", checks);
        else
            $display("%0d OF %0d CHECKS FAILED", errors, checks);
        $display("--------------------------------------------------");

        $finish;
    end

endmodule

top_tb.vcd
$version Generated by VerilatedVcd $end
$timescale 1ps $end
 $scope module $rootio $end
 $upscope $end
 $scope module top_tb $end
  $var wire 1 V clk $end
  $var wire 1 W rst $end
  $var wire 32 X errors [31:0] $end
  $var wire 32 Y checks [31:0] $end
  $scope module dut $end
   $var wire 1 V clk $end
   $var wire 1 W rst $end
   $var wire 32 3 pc_out [31:0] $end
   $var wire 32 4 pc_plus_4 [31:0] $end
   $var wire 32 Z pc_next [31:0] $end
   $var wire 32 [ branch_target [31:0] $end
   $var wire 32 # instr [31:0] $end
   $var wire 32 $ rs1_data [31:0] $end
   $var wire 32 \ rs2_data [31:0] $end
   $var wire 32 % alu_b [31:0] $end
   $var wire 32 & alu_result [31:0] $end
   $var wire 32 ' imm [31:0] $end
   $var wire 1 ( reg_write $end
   $var wire 1 ) alu_src $end
   $var wire 1 * branch $end
   $var wire 1 + zero $end
   $var wire 1 ] branch_taken $end
   $var wire 4 , alu_ctrl [3:0] $end
   $var wire 7 - opcode [6:0] $end
   $var wire 5 . rd_addr [4:0] $end
   $var wire 3 / funct3 [2:0] $end
   $var wire 5 0 rs1_addr [4:0] $end
   $var wire 5 1 rs2_addr [4:0] $end
   $var wire 1 2 funct7_b5 $end
   $scope module alu_inst $end
    $var wire 32 $ a [31:0] $end
    $var wire 32 % b [31:0] $end
    $var wire 4 , alu_ctrl [3:0] $end
    $var wire 32 & result [31:0] $end
    $var wire 1 + zero $end
    $var wire 4 _ ALU_ADD [3:0] $end
    $var wire 4 ` ALU_SUB [3:0] $end
    $var wire 4 a ALU_AND [3:0] $end
    $var wire 4 b ALU_OR [3:0] $end
    $var wire 4 c ALU_XOR [3:0] $end
    $var wire 4 d ALU_SLL [3:0] $end
    $var wire 4 e ALU_SRL [3:0] $end
    $var wire 4 f ALU_SRA [3:0] $end
    $var wire 4 g ALU_SLT [3:0] $end
    $var wire 4 h ALU_SLTU [3:0] $end
   $upscope $end
   $scope module control_inst $end
    $var wire 7 - opcode [6:0] $end
    $var wire 3 / funct3 [2:0] $end
    $var wire 1 2 funct7_b5 $end
    $var wire 1 ( reg_write $end
    $var wire 1 ) alu_src $end
    $var wire 1 * branch $end
    $var wire 4 , alu_ctrl [3:0] $end
    $var wire 7 i OP_R_TYPE [6:0] $end
    $var wire 7 j OP_I_TYPE [6:0] $end
    $var wire 7 k OP_B_TYPE [6:0] $end
    $var wire 4 _ ALU_ADD [3:0] $end
    $var wire 4 ` ALU_SUB [3:0] $end
    $var wire 4 a ALU_AND [3:0] $end
    $var wire 4 b ALU_OR [3:0] $end
    $var wire 4 c ALU_XOR [3:0] $end
    $var wire 4 d ALU_SLL [3:0] $end
    $var wire 4 e ALU_SRL [3:0] $end
    $var wire 4 f ALU_SRA [3:0] $end
    $var wire 4 g ALU_SLT [3:0] $end
    $var wire 4 h ALU_SLTU [3:0] $end
   $upscope $end
   $scope module imem_inst $end
    $var wire 32 l MEM_SIZE_WORDS [31:0] $end
    $var wire 32 3 addr [31:0] $end
    $var wire 32 # instr [31:0] $end
    $var wire 32 ^ i [31:0] $end
    $var wire 32 m ADDR_WIDTH [31:0] $end
   $upscope $end
   $scope module immgen_inst $end
    $var wire 32 # instr [31:0] $end
    $var wire 32 ' imm [31:0] $end
    $var wire 7 j OP_I_TYPE [6:0] $end
    $var wire 7 k OP_B_TYPE [6:0] $end
   $upscope $end
   $scope module pc_inst $end
    $var wire 1 V clk $end
    $var wire 1 W rst $end
    $var wire 32 Z pc_next [31:0] $end
    $var wire 32 3 pc_out [31:0] $end
   $upscope $end
   $scope module regfile_inst $end
    $var wire 1 V clk $end
    $var wire 1 W rst $end
    $var wire 5 0 rs1_addr [4:0] $end
    $var wire 5 1 rs2_addr [4:0] $end
    $var wire 5 . rd_addr [4:0] $end
    $var wire 32 & rd_data [31:0] $end
    $var wire 1 ( reg_write $end
    $var wire 32 $ rs1_data [31:0] $end
    $var wire 32 \ rs2_data [31:0] $end
    $var wire 32 5 registers[0] [31:0] $end
    $var wire 32 6 registers[1] [31:0] $end
    $var wire 32 7 registers[2] [31:0] $end
    $var wire 32 8 registers[3] [31:0] $end
    $var wire 32 9 registers[4] [31:0] $end
    $var wire 32 : registers[5] [31:0] $end
    $var wire 32 ; registers[6] [31:0] $end
    $var wire 32 < registers[7] [31:0] $end
    $var wire 32 = registers[8] [31:0] $end
    $var wire 32 > registers[9] [31:0] $end
    $var wire 32 ? registers[10] [31:0] $end
    $var wire 32 @ registers[11] [31:0] $end
    $var wire 32 A registers[12] [31:0] $end
    $var wire 32 B registers[13] [31:0] $end
    $var wire 32 C registers[14] [31:0] $end
    $var wire 32 D registers[15] [31:0] $end
    $var wire 32 E registers[16] [31:0] $end
    $var wire 32 F registers[17] [31:0] $end
    $var wire 32 G registers[18] [31:0] $end
    $var wire 32 H registers[19] [31:0] $end
    $var wire 32 I registers[20] [31:0] $end
    $var wire 32 J registers[21] [31:0] $end
    $var wire 32 K registers[22] [31:0] $end
    $var wire 32 L registers[23] [31:0] $end
    $var wire 32 M registers[24] [31:0] $end
    $var wire 32 N registers[25] [31:0] $end
    $var wire 32 O registers[26] [31:0] $end
    $var wire 32 P registers[27] [31:0] $end
    $var wire 32 Q registers[28] [31:0] $end
    $var wire 32 R registers[29] [31:0] $end
    $var wire 32 S registers[30] [31:0] $end
    $var wire 32 T registers[31] [31:0] $end
    $var wire 32 U i [31:0] $end
   $upscope $end
  $upscope $end
 $upscope $end
$enddefinitions $end


#0
b00000000010100000000000010010011 #
b00000000000000000000000000000000 $
b00000000000000000000000000000101 %
b00000000000000000000000000000101 &
b00000000000000000000000000000101 '
1(
1)
0*
0+
b0000 ,
b0010011 -
b00001 .
b000 /
b00000 0
b00101 1
02
b00000000000000000000000000000000 3
b00000000000000000000000000000100 4
b00000000000000000000000000000000 5
b00000000000000000000000000000000 6
b00000000000000000000000000000000 7
b00000000000000000000000000000000 8
b00000000000000000000000000000000 9
b00000000000000000000000000000000 :
b00000000000000000000000000000000 ;
b00000000000000000000000000000000 <
b00000000000000000000000000000000 =
b00000000000000000000000000000000 >
b00000000000000000000000000000000 ?
b00000000000000000000000000000000 @
b00000000000000000000000000000000 A
b00000000000000000000000000000000 B
b00000000000000000000000000000000 C
b00000000000000000000000000000000 D
b00000000000000000000000000000000 E
b00000000000000000000000000000000 F
b00000000000000000000000000000000 G
b00000000000000000000000000000000 H
b00000000000000000000000000000000 I
b00000000000000000000000000000000 J
b00000000000000000000000000000000 K
b00000000000000000000000000000000 L
b00000000000000000000000000000000 M
b00000000000000000000000000000000 N
b00000000000000000000000000000000 O
b00000000000000000000000000000000 P
b00000000000000000000000000000000 Q
b00000000000000000000000000000000 R
b00000000000000000000000000000000 S
b00000000000000000000000000000000 T
b00000000000000000000000000000000 U
0V
1W
b00000000000000000000000000000000 X
b00000000000000000000000000000000 Y
b00000000000000000000000000000100 Z
b00000000000000000000000000000101 [
b00000000000000000000000000000000 \
0]
b00000000000000000000000100000000 ^
b0000 _
b0001 `
b0010 a
b0011 b
b0100 c
b0101 d
b0110 e
b0111 f
b1000 g
b1001 h
b0110011 i
b0010011 j
b1100011 k
b00000000000000000000000100000000 l
b00000000000000000000000000001000 m
#5000
b00000000000000000000000000100000 U
1V
#6000
0W
#10000
0V
#15000
b00000000101000000000000100010011 #
b00000000000000000000000000001010 %
b00000000000000000000000000001010 &
b00000000000000000000000000001010 '
b00010 .
b01010 1
b00000000000000000000000000000100 3
b00000000000000000000000000001000 4
b00000000000000000000000000000101 6
1V
b00000000000000000000000000001000 Z
b00000000000000000000000000001110 [
#20000
0V
#25000
b00000000001000001000000110110011 #
b00000000000000000000000000000101 $
b00000000000000000000000000001111 &
b00000000000000000000000000000000 '
0)
b0110011 -
b00011 .
b00001 0
b00010 1
b00000000000000000000000000001000 3
b00000000000000000000000000001100 4
b00000000000000000000000000001010 7
1V
b00000000000000000000000000001100 Z
b00000000000000000000000000001000 [
b00000000000000000000000000001010 \
#30000
0V
#35000
b01000000000100010000001000110011 #
b00000000000000000000000000001010 $
b00000000000000000000000000000101 %
b00000000000000000000000000000101 &
b0001 ,
b00100 .
b00010 0
b00001 1
12
b00000000000000000000000000001100 3
b00000000000000000000000000010000 4
b00000000000000000000000000001111 8
1V
b00000000000000000000000000010000 Z
b00000000000000000000000000001100 [
b00000000000000000000000000000101 \
#40000
0V
#45000
b00000000010000001000010001100011 #
b00000000000000000000000000000101 $
b00000000000000000000000000000000 &
b00000000000000000000000000001000 '
0(
1*
1+
b1100011 -
b01000 .
b00001 0
b00100 1
02
b00000000000000000000000000010000 3
b00000000000000000000000000010100 4
b00000000000000000000000000000101 9
1V
b00000000000000000000000000011000 Z
b00000000000000000000000000011000 [
1]
#50000
0V
#55000
b00000000000100000000001100010011 #
b00000000000000000000000000000000 $
b00000000000000000000000000000001 %
b00000000000000000000000000000001 &
b00000000000000000000000000000001 '
1(
1)
0*
0+
b0000 ,
b0010011 -
b00110 .
b00000 0
b00001 1
b00000000000000000000000000011000 3
b00000000000000000000000000011100 4
1V
b00000000000000000000000000011100 Z
b00000000000000000000000000011001 [
0]
#60000
0V
#65000
b00000000000000000000000000000000 #
b00000000000000000000000000000000 %
b00000000000000000000000000000000 &
b00000000000000000000000000000000 '
0(
0)
1+
b0000000 -
b00000 .
b00000 1
b00000000000000000000000000011100 3
b00000000000000000000000000100000 4
b00000000000000000000000000000001 ;
1V
b00000000000000000000000000100000 Z
b00000000000000000000000000011100 [
b00000000000000000000000000000000 \
#70000
0V
#75000
b00000000000000000000000000100000 3
b00000000000000000000000000100100 4
1V
b00000000000000000000000000100100 Z
b00000000000000000000000000100000 [
#76000
b00000000000000000000000000000110 Y
