src/pc.v
`timescale 1ns / 1ps

module pc (
    input wire clk,
    input wire rst,
    input wire [31:0] pc_next,
    output reg [31:0] pc_out
    );

always @(posedge clk or posedge rst) begin
    if (rst)
        pc_out <= 32'b00; // Reset PC to 0 on reset
    else
        pc_out <= pc_next; // Update PC with the next value
end

endmodule

tests/pc_tb.v
`timescale 1ns / 1ps

module pc_tb;

    // DUT signals
    reg         clk;
    reg         rst;
    reg  [31:0] pc_next;
    wire [31:0] pc_out;

    integer     errors = 0;
    integer     checks = 0;

    // Instantiate the PC
    pc dut (
        .clk     (clk),
        .rst     (rst),
        .pc_next (pc_next),
        .pc_out  (pc_out)
    );

    // 100 MHz clock: 10ns period
    initial clk = 0;
    always #5 clk = ~clk;

    // Task to check pc_out against an expected value after the next clock edge
    task check_pc(input [31:0] expected, input string label);
        begin
            @(posedge clk);
            #1; // small delta delay to let non-blocking assignment settle
            checks = checks + 1;
            if (pc_out !== expected) begin
                errors = errors + 1;
                $display("[FAIL] %0s: expected pc_out=0x%08h, got 0x%08h at time %0t",
                          label, expected, pc_out, $time);
            end else begin
                $display("[PASS] %0s: pc_out=0x%08h at time %0t",
                          label, pc_out, $time);
            end
        end
    endtask

    initial begin
        // Optional waveform dump for GTKWave/Verilator trace viewing
        $dumpfile("pc_tb.vcd");
        $dumpvars(0, pc_tb);

        // --- Test 1: Reset behavior ---
        rst     = 1;
        pc_next = 32'hDEAD_BEEF; // garbage on pc_next; reset should override it
        @(posedge clk);
        #1;
        checks = checks + 1;
        if (pc_out !== 32'h0) begin
            errors = errors + 1;
            $display("[FAIL] Reset: expected pc_out=0x00000000, got 0x%08h at time %0t",
                      pc_out, $time);
        end else begin
            $display("[PASS] Reset: pc_out=0x%08h at time %0t", pc_out, $time);
        end

        // --- Test 2: Normal sequential update after reset deasserts ---
        rst     = 0;
        pc_next = 32'h0000_0004;
        check_pc(32'h0000_0004, "Sequential +4 update");

        // --- Test 3: Branch/jump-style non-sequential update ---
        pc_next = 32'h0000_1000;
        check_pc(32'h0000_1000, "Jump to arbitrary address");

        // --- Test 4: Another sequential step from the jumped-to address ---
        pc_next = 32'h0000_1004;
        check_pc(32'h0000_1004, "Sequential +4 after jump");

        // --- Test 5: Mid-operation reset ---
        rst = 1;
        @(posedge clk);
        #1;
        checks = checks + 1;
        if (pc_out !== 32'h0) begin
            errors = errors + 1;
            $display("[FAIL] Mid-op reset: expected pc_out=0x00000000, got 0x%08h at time %0t",
                      pc_out, $time);
        end else begin
            $display("[PASS] Mid-op reset: pc_out=0x%08h at time %0t", pc_out, $time);
        end
        rst = 0;

        // --- Test 6: Wraparound-style large address ---
        pc_next = 32'hFFFF_FFFC;
        check_pc(32'hFFFF_FFFC, "Large address update");

        // --- Test 7: Double jump (two jumps back-to-back, no sequential step between) ---
        pc_next = 32'h0000_2000;
        check_pc(32'h0000_2000, "First Jump");

        pc_next = 32'h0000_3000;
        check_pc(32'h0000_3000, "Second Jump");

        // --- Summary ---
        $display("--------------------------------------------------");
        if (errors == 0)
            $display("ALL %0d CHECKS PASSED", checks);
        else
            $display("%0d OF %0d CHECKS FAILED", errors, checks);
        $display("--------------------------------------------------");

        $finish;
    end

endmodule

tests/pc_tb.vcd
$version Generated by VerilatedVcd $end
$timescale 1ps $end
 $scope module $rootio $end
 $upscope $end
 $scope module pc_tb $end
  $var wire 1 # clk $end
  $var wire 1 $ rst $end
  $var wire 32 % pc_next [31:0] $end
  $var wire 32 & pc_out [31:0] $end
  $var wire 32 ' errors [31:0] $end
  $var wire 32 ( checks [31:0] $end
  $scope module dut $end
   $var wire 1 # clk $end
   $var wire 1 $ rst $end
   $var wire 32 % pc_next [31:0] $end
   $var wire 32 & pc_out [31:0] $end
  $upscope $end
 $upscope $end
$enddefinitions $end


#0
0#
1$
b11011110101011011011111011101111 %
b00000000000000000000000000000000 &
b00000000000000000000000000000000 '
b00000000000000000000000000000000 (
#5000
1#
#6000
0$
b00000000000000000000000000000100 %
b00000000000000000000000000000001 (
#10000
0#
#15000
1#
b00000000000000000000000000000100 &
#16000
b00000000000000000001000000000000 %
b00000000000000000000000000000010 (
#20000
0#
#25000
1#
b00000000000000000001000000000000 &
#26000
b00000000000000000001000000000100 %
b00000000000000000000000000000011 (
#30000
0#
#35000
1#
b00000000000000000001000000000100 &
#36000
1$
b00000000000000000000000000000000 &
b00000000000000000000000000000100 (
#40000
0#
#45000
1#
#46000
0$
b11111111111111111111111111111100 %
b00000000000000000000000000000101 (
#50000
0#
#55000
1#
b11111111111111111111111111111100 &
#56000
b00000000000000000010000000000000 %
b00000000000000000000000000000110 (
#60000
0#
#65000
1#
b00000000000000000010000000000000 &
#66000
b00000000000000000011000000000000 %
b00000000000000000000000000000111 (
#70000
0#
#75000
1#
b00000000000000000011000000000000 &
#76000
b00000000000000000000000000001000 (
