src/regfile.v
`timescale 1ns / 1ps

module regfile (
    input wire clk,
    input wire rst,
    input wire [4:0] rs1_addr,
    input wire [4:0] rs2_addr,
    input wire [4:0] rd_addr,
    input wire [31:0] rd_data,
    input wire reg_write,
    output reg [31:0] rs1_data,
    output reg [31:0] rs2_data
);

    // Register file: 32 registers of 32 bits each
    reg [31:0] registers [31:0];

    // Initialize registers to zero on reset
    integer i;
    always @(posedge clk or posedge rst) begin
        if (rst) begin
            for (i = 0; i < 32; i = i + 1) begin
                registers[i] <= 32'b0;
            end
        end else if (reg_write && rd_addr != 5'b00000) begin
            // Write to the register file on the rising edge of the clock
            registers[rd_addr] <= rd_data;
        end
    end

    // --- Read logic: combinational, always available ---
    // x0 is hardwired to zero: if either read address is 0, force output
    // to 0 regardless of what's actually stored there (which will also be
    // 0 after reset, but this makes the guarantee explicit and independent
    // of reset having run).
    assign rs1_data = (rs1_addr == 5'b0) ? 32'b0 : registers[rs1_addr];
    assign rs2_data = (rs2_addr == 5'b0) ? 32'b0 : registers[rs2_addr];

endmodule

tests/regfile_tb.v
`timescale 1ns / 1ps

module regfile_tb;

    reg         clk;
    reg         rst;
    reg  [4:0]  rs1_addr;
    reg  [4:0]  rs2_addr;
    wire [31:0] rs1_data;
    wire [31:0] rs2_data;
    reg         reg_write;
    reg  [4:0]  rd_addr;
    reg  [31:0] rd_data;

    integer     errors = 0;
    integer     checks = 0;

    regfile dut (
        .clk       (clk),
        .rst       (rst),
        .rs1_addr  (rs1_addr),
        .rs1_data  (rs1_data),
        .rs2_addr  (rs2_addr),
        .rs2_data  (rs2_data),
        .reg_write (reg_write),
        .rd_addr   (rd_addr),
        .rd_data   (rd_data)
    );

    initial clk = 0;
    always #5 clk = ~clk;

    // Writes a value into a register on the next clock edge
    task do_write(input [4:0] addr, input [31:0] data);
        begin
            rd_addr   = addr;
            rd_data   = data;
            reg_write = 1;
            @(posedge clk);
            #1;
            reg_write = 0;
        end
    endtask

    // Checks that a given register currently reads back the expected value
    // via read port 1 (combinational -- no clock edge needed to see it)
    task check_read(input [4:0] addr, input [31:0] expected, input string label);
        begin
            rs1_addr = addr;
            #1; // allow combinational logic to settle
            checks = checks + 1;
            if (rs1_data !== expected) begin
                errors = errors + 1;
                $display("[FAIL] %0s: reg[%0d] expected 0x%08h, got 0x%08h at time %0t",
                          label, addr, expected, rs1_data, $time);
            end else begin
                $display("[PASS] %0s: reg[%0d] = 0x%08h at time %0t",
                          label, addr, rs1_data, $time);
            end
        end
    endtask

    initial begin
        $dumpfile("regfile_tb.vcd");
        $dumpvars(0, regfile_tb);

        // --- Test 1: Reset clears all registers ---
        rst       = 1;
        reg_write = 0;
        rd_addr   = 5'd0;
        rd_data   = 32'd0;
        rs1_addr  = 5'd5;
        rs2_addr  = 5'd10;
        @(posedge clk);
        #1;
        checks = checks + 1;
        if (rs1_data !== 32'b0 || rs2_data !== 32'b0) begin
            errors = errors + 1;
            $display("[FAIL] Reset: expected both read ports 0, got rs1=0x%08h rs2=0x%08h",
                      rs1_data, rs2_data);
        end else begin
            $display("[PASS] Reset: all registers cleared");
        end
        rst = 0;

        // --- Test 2: Basic write then read back ---
        do_write(5'd1, 32'hDEAD_BEEF);
        check_read(5'd1, 32'hDEAD_BEEF, "Write/read x1");

        // --- Test 3: x0 always reads zero, even if we try to write it ---
        do_write(5'd0, 32'hFFFF_FFFF);
        check_read(5'd0, 32'h0000_0000, "x0 stays zero after attempted write");

        // --- Test 4: Writing a different register doesn't disturb x1 ---
        do_write(5'd2, 32'h1234_5678);
        check_read(5'd1, 32'hDEAD_BEEF, "x1 unaffected by writing x2");
        check_read(5'd2, 32'h1234_5678, "x2 holds its own value");

        // --- Test 5: Both read ports work independently and simultaneously ---
        rs1_addr = 5'd1;
        rs2_addr = 5'd2;
        #1;
        checks = checks + 1;
        if (rs1_data !== 32'hDEAD_BEEF || rs2_data !== 32'h1234_5678) begin
            errors = errors + 1;
            $display("[FAIL] Dual-port read: expected rs1=0xDEADBEEF rs2=0x12345678, got rs1=0x%08h rs2=0x%08h",
                      rs1_data, rs2_data);
        end else begin
            $display("[PASS] Dual-port read: rs1=0x%08h rs2=0x%08h simultaneously", rs1_data, rs2_data);
        end

        // --- Test 6: reg_write deasserted means no write happens ---
        rd_addr   = 5'd3;
        rd_data   = 32'hAAAA_AAAA;
        reg_write = 0; // deliberately NOT enabling write
        @(posedge clk);
        #1;
        check_read(5'd3, 32'h0000_0000, "x3 unwritten when reg_write=0");

        // --- Test 7: Overwriting an existing register updates it ---
        do_write(5'd1, 32'h0000_0001);
        check_read(5'd1, 32'h0000_0001, "x1 overwritten with new value");

        // --- Test 8: Reading rs1 == rs2 (same register on both ports) ---
        rs1_addr = 5'd2;
        rs2_addr = 5'd2;
        #1;
        checks = checks + 1;
        if (rs1_data !== 32'h1234_5678 || rs2_data !== 32'h1234_5678) begin
            errors = errors + 1;
            $display("[FAIL] Same-register dual read: expected both 0x12345678, got rs1=0x%08h rs2=0x%08h",
                      rs1_data, rs2_data);
        end else begin
            $display("[PASS] Same-register dual read: rs1=rs2=0x%08h", rs1_data);
        end

        // --- Test 9: Checks for old values ---
        rs1_addr = 5'd1;
        rd_addr = 5'd1;
        rd_data = 32'h0000_0011;
        reg_write = 1;

        #1;
        checks = checks + 1;
        if (rs1_data !== 32'h0000_0001) begin
            errors = errors + 1;
            $display("[FAIL] Old value check: expected rs1=0x00000001, got 0x%08h", rs1_data);
        end else begin  
            $display("[PASS] Old value check: rs1=0x%08h", rs1_data);
        end

        @(posedge clk);
        #1;
        reg_write = 0;


        // --- Summary of all checks ---
        checks = checks + 1;
        if (rs1_data !== 32'h0000_0011) begin
            errors = errors + 1;
            $display("[FAIL] New value check: expected rs1=0x00000011, got 0x%08h", rs1_data);
        end else begin
            $display("[PASS] New value check: rs1=0x%08h", rs1_data);
        end

                $display("--------------------------------------------------");
        if (errors == 0)
            $display("ALL %0d CHECKS PASSED", checks);
        else
            $display("%0d OF %0d CHECKS FAILED", errors, checks);
        $display("--------------------------------------------------");

        $finish;
    end

endmodule

tests/regfile_tb.vcd
$version Generated by VerilatedVcd $end
$timescale 1ps $end
 $scope module $rootio $end
 $upscope $end
 $scope module regfile_tb $end
  $var wire 1 L clk $end
  $var wire 1 # rst $end
  $var wire 5 $ rs1_addr [4:0] $end
  $var wire 5 % rs2_addr [4:0] $end
  $var wire 32 M rs1_data [31:0] $end
  $var wire 32 N rs2_data [31:0] $end
  $var wire 1 & reg_write $end
  $var wire 5 ' rd_addr [4:0] $end
  $var wire 32 ( rd_data [31:0] $end
  $var wire 32 ) errors [31:0] $end
  $var wire 32 * checks [31:0] $end
  $scope module dut $end
   $var wire 1 L clk $end
   $var wire 1 # rst $end
   $var wire 5 $ rs1_addr [4:0] $end
   $var wire 5 % rs2_addr [4:0] $end
   $var wire 5 ' rd_addr [4:0] $end
   $var wire 32 ( rd_data [31:0] $end
   $var wire 1 & reg_write $end
   $var wire 32 M rs1_data [31:0] $end
   $var wire 32 N rs2_data [31:0] $end
   $var wire 32 + registers[0] [31:0] $end
   $var wire 32 , registers[1] [31:0] $end
   $var wire 32 - registers[2] [31:0] $end
   $var wire 32 . registers[3] [31:0] $end
   $var wire 32 / registers[4] [31:0] $end
   $var wire 32 0 registers[5] [31:0] $end
   $var wire 32 1 registers[6] [31:0] $end
   $var wire 32 2 registers[7] [31:0] $end
   $var wire 32 3 registers[8] [31:0] $end
   $var wire 32 4 registers[9] [31:0] $end
   $var wire 32 5 registers[10] [31:0] $end
   $var wire 32 6 registers[11] [31:0] $end
   $var wire 32 7 registers[12] [31:0] $end
   $var wire 32 8 registers[13] [31:0] $end
   $var wire 32 9 registers[14] [31:0] $end
   $var wire 32 : registers[15] [31:0] $end
   $var wire 32 ; registers[16] [31:0] $end
   $var wire 32 < registers[17] [31:0] $end
   $var wire 32 = registers[18] [31:0] $end
   $var wire 32 > registers[19] [31:0] $end
   $var wire 32 ? registers[20] [31:0] $end
   $var wire 32 @ registers[21] [31:0] $end
   $var wire 32 A registers[22] [31:0] $end
   $var wire 32 B registers[23] [31:0] $end
   $var wire 32 C registers[24] [31:0] $end
   $var wire 32 D registers[25] [31:0] $end
   $var wire 32 E registers[26] [31:0] $end
   $var wire 32 F registers[27] [31:0] $end
   $var wire 32 G registers[28] [31:0] $end
   $var wire 32 H registers[29] [31:0] $end
   $var wire 32 I registers[30] [31:0] $end
   $var wire 32 J registers[31] [31:0] $end
   $var wire 32 K i [31:0] $end
  $upscope $end
 $upscope $end
$enddefinitions $end


#0
1#
b00101 $
b01010 %
0&
b00000 '
b00000000000000000000000000000000 (
b00000000000000000000000000000000 )
b00000000000000000000000000000000 *
b00000000000000000000000000000000 +
b00000000000000000000000000000000 ,
b00000000000000000000000000000000 -
b00000000000000000000000000000000 .
b00000000000000000000000000000000 /
b00000000000000000000000000000000 0
b00000000000000000000000000000000 1
b00000000000000000000000000000000 2
b00000000000000000000000000000000 3
b00000000000000000000000000000000 4
b00000000000000000000000000000000 5
b00000000000000000000000000000000 6
b00000000000000000000000000000000 7
b00000000000000000000000000000000 8
b00000000000000000000000000000000 9
b00000000000000000000000000000000 :
b00000000000000000000000000000000 ;
b00000000000000000000000000000000 <
b00000000000000000000000000000000 =
b00000000000000000000000000000000 >
b00000000000000000000000000000000 ?
b00000000000000000000000000000000 @
b00000000000000000000000000000000 A
b00000000000000000000000000000000 B
b00000000000000000000000000000000 C
b00000000000000000000000000000000 D
b00000000000000000000000000000000 E
b00000000000000000000000000000000 F
b00000000000000000000000000000000 G
b00000000000000000000000000000000 H
b00000000000000000000000000000000 I
b00000000000000000000000000000000 J
b00000000000000000000000000000000 K
0L
b00000000000000000000000000000000 M
b00000000000000000000000000000000 N
#5000
b00000000000000000000000000100000 K
1L
#6000
0#
1&
b00001 '
b11011110101011011011111011101111 (
b00000000000000000000000000000001 *
#10000
0L
#15000
b11011110101011011011111011101111 ,
1L
#16000
b00001 $
0&
b11011110101011011011111011101111 M
#17000
1&
b00000 '
b11111111111111111111111111111111 (
b00000000000000000000000000000010 *
#20000
0L
#25000
1L
#26000
b00000 $
0&
b00000000000000000000000000000000 M
#27000
1&
b00010 '
b00010010001101000101011001111000 (
b00000000000000000000000000000011 *
#30000
0L
#35000
b00010010001101000101011001111000 -
1L
#36000
b00001 $
0&
b11011110101011011011111011101111 M
#37000
b00010 $
b00000000000000000000000000000100 *
b00010010001101000101011001111000 M
#38000
b00001 $
b00010 %
b00000000000000000000000000000101 *
b11011110101011011011111011101111 M
b00010010001101000101011001111000 N
#39000
b00011 '
b10101010101010101010101010101010 (
b00000000000000000000000000000110 *
#40000
0L
#45000
1L
#46000
b00011 $
b00000000000000000000000000000000 M
#47000
1&
b00001 '
b00000000000000000000000000000001 (
b00000000000000000000000000000111 *
#50000
0L
#55000
b00000000000000000000000000000001 ,
1L
#56000
b00001 $
0&
b00000000000000000000000000000001 M
#57000
b00010 $
b00000000000000000000000000001000 *
b00010010001101000101011001111000 M
#58000
b00001 $
1&
b00000000000000000000000000010001 (
b00000000000000000000000000001001 *
b00000000000000000000000000000001 M
#59000
b00000000000000000000000000001010 *
#60000
0L
#65000
b00000000000000000000000000010001 ,
1L
b00000000000000000000000000010001 M
#66000
0&
b00000000000000000000000000001011 *
